migrations/0001_initial.py
migrations/__init__.py
list_basculas-0.2.dist-info/METADATA
list_basculas-0.2.dist-info/WHEEL
list_basculas-0.2.dist-info/top_level.txt
list_basculas-0.2.dist-info/RECORD
